langchain_moorcheh/__init__.py
langchain_moorcheh/py.typed
langchain_moorcheh/vectorstores.py
langchain_moorcheh-0.1.1.dist-info/LICENSE
langchain_moorcheh-0.1.1.dist-info/METADATA
langchain_moorcheh-0.1.1.dist-info/WHEEL
langchain_moorcheh-0.1.1.dist-info/RECORD
