Metadata-Version: 2.3
Name: langchain-moorcheh
Version: 0.1.1
Summary: An integration package connecting Moorcheh and LangChain
License: MIT
Keywords: langchain,moorcheh,vectorstore,ai,embeddings
Author: Moorcheh AI
Author-email: support@moorcheh.ai
Requires-Python: >=3.10,<4.0
Classifier: Intended Audience :: Developers
Classifier: License :: OSI Approved :: MIT License
Classifier: Programming Language :: Python :: 3
Classifier: Programming Language :: Python :: 3.10
Classifier: Programming Language :: Python :: 3.11
Classifier: Programming Language :: Python :: 3.12
Classifier: Programming Language :: Python :: 3.13
Requires-Dist: langchain (>=0.3.27,<0.4.0)
Requires-Dist: langchain-core (>=0.3.15,<0.4.0)
Requires-Dist: langchain-openai (>=0.3.28,<0.4.0)
Requires-Dist: moorcheh-sdk (>=1.2.0,<2.0.0)
Project-URL: Repository, https://github.com/moorcheh-ai/langchain-moorcheh
Project-URL: Release Notes, https://github.com/moorcheh-ai/langchain-moorcheh/releases
Project-URL: Source Code, https://github.com/moorcheh-ai/langchain-moorcheh
